dojo/config/data/abis/AAVE/FlashLoanReciever.json
dojo/config/data/abis/AaveV3/ACLManager.json
dojo/config/data/abis/AaveV3/AaveOracle.json
dojo/config/data/abis/AaveV3/CompassOracle.json
dojo/config/data/abis/AaveV3/FlashLoanReciever.json
dojo/config/data/abis/AaveV3/Incentives.json
dojo/config/data/abis/AaveV3/Pool.json
dojo/config/data/abis/AaveV3/PoolAddressesProvider.json
dojo/config/data/abis/AaveV3/PoolConfigurator.json
dojo/config/data/abis/AaveV3/UiPoolDataProviderV3.json
dojo/config/data/abis/AaveV3/WalletBalanceProvider.json
dojo/config/data/abis/BalancerV2/BalV2Vault.json
dojo/config/data/abis/BalancerV2/ComposableStablePool.json
dojo/config/data/abis/BalancerV2/GaugeFactory.json
dojo/config/data/abis/BalancerV2/GaugeV5.json
dojo/config/data/abis/BalancerV2/Weighted2Pool.json
dojo/config/data/abis/BalancerV2/WeightedPool.json
dojo/config/data/abis/ERC20.json
dojo/config/data/abis/ERC721.json
dojo/config/data/abis/Tokens/USDC.json
dojo/config/data/abis/Tokens/WETH.json
dojo/config/data/abis/UniswapV3/NonfungiblePositionManager.json
dojo/config/data/abis/UniswapV3/NonfungibleTokenPositionDescriptor.json
dojo/config/data/abis/UniswapV3/SwapRouter.json
dojo/config/data/abis/UniswapV3/UniV3Factory.json
dojo/config/data/abis/UniswapV3/UniV3Pool.json
dojo/config/data/bytecodes/AAVE/FlashLoanReciever.bytecode
dojo/config/data/bytecodes/AaveV3/CompassOracle.bytecode
dojo/config/data/bytecodes/AaveV3/FlashLoanReciever.bytecode
dojo/config/data/bytecodes/AaveV3/UiPoolDataProviderV3.bytecode
dojo/config/data/bytecodes/ERC20.bytecode
dojo/config/data/bytecodes/Tokens/USDC.bytecode
dojo/config/data/bytecodes/Tokens/WETH.bytecode
dojo/config/data/bytecodes/UniswapV3/NonfungiblePositionManager.bytecode
dojo/config/data/bytecodes/UniswapV3/NonfungibleTokenPositionDescriptor.bytecode
dojo/config/data/bytecodes/UniswapV3/SwapRouter.bytecode
dojo/config/data/bytecodes/UniswapV3/UniV3Factory.bytecode
dojo/config/data/contracts/CompassOracle.sol
dojo_compass-2.3.3.dist-info/METADATA
dojo_compass-2.3.3.dist-info/WHEEL
dojo_compass-2.3.3.dist-info/entry_points.txt
dojo_compass-2.3.3.dist-info/RECORD
