Metadata-Version: 2.1
Name: dojo-compass
Version: 2.3.3
Summary: Realistic DeFi simulations
Keywords: defi,uniswap,AMM,simulation,crypto,realistic,on-chain
Author: Compass Labs
Requires-Python: >=3.9,<3.13
Classifier: Programming Language :: Python :: 3
Classifier: Programming Language :: Python :: 3.9
Classifier: Programming Language :: Python :: 3.10
Classifier: Programming Language :: Python :: 3.11
Requires-Dist: Cython (>=3.0.0)
Requires-Dist: blosc (>=1.11.1,<2.0.0)
Requires-Dist: boto3 (>=1.26.140,<2.0.0)
Requires-Dist: dash (>=2.10.2,<3.0.0)
Requires-Dist: dash-bootstrap-components (>=1.4.1,<2.0.0)
Requires-Dist: dash-mantine-components (>=0.12.1,<0.13.0)
Requires-Dist: frozendict (>=2.3.8,<3.0.0)
Requires-Dist: google-auth (>=2.23.4,<3.0.0)
Requires-Dist: google-cloud-bigquery (>=3.13.0,<4.0.0)
Requires-Dist: jsons (>=1.6.3,<2.0.0)
Requires-Dist: matplotlib (>=3.5.2,<4.0.0)
Requires-Dist: numpy (>=1.21.1,<2.0.0)
Requires-Dist: pathlib (>=1.0.1,<2.0.0)
Requires-Dist: py-machineid (>=0.3.0,<0.4.0)
Requires-Dist: py-solc-x (>=1.1.1,<2.0.0)
Requires-Dist: python-dotenv (>=1.0.0,<2.0.0)
Requires-Dist: pytz (>=2023.3,<2024.0)
Requires-Dist: tqdm (>=4.65.0,<5.0.0)
Requires-Dist: ujson (>=5.8.0,<6.0.0)
Requires-Dist: waitress (>=2.1.2,<3.0.0)
Requires-Dist: web3 (>=6.8.0,<7.0.0)
Project-URL: Documentation, https://dojo.compasslabs.ai
